{
	"event":
	{
		"eventID": 3,
		"bg": "gamebg_event05",
		"bg2": "gamebg_event05b",
		"button": "ranking_icon_201605",
		"endButton": "ranking_icon_201605end",
		"rank": "bu_pointevent_3",
		"reward": "bu_pointevent_2",
		"help": "bu_pointevent_4",
		"charList": "bu_pointevent_5",
		"resultNPC": "npc2",
		"startTime": "13-5-2016 16:0:0",
		"endTime": "19-5-2016 23:59:59"
	},	
	
	"button":
	[
		{
			"eventID": 0,
			"questId": 29019,
			"zoneId": 0,
			"icon": "bu_pointevent_0",
			"startTime": "13-5-2016 16:0:0",
			"endTime": "19-5-2016 23:59:59"
		}
	],
	
	"help":	
	[
	"Tutor_Battle_01",
	"Tutor_Battle_02",
	"Tutor_Battle_03",
	"Tutor_Battle_04"
	],
	
	"char":
	{
		"205": 0.025,
		"206": 0.05,
		"343": 0.025,
		"344": 0.05,
		"737": 0.025,
		"738": 0.05,
		"699": 0.025,
		"700": 0.05,
		"247": 0.025,
		"248": 0.05,
		"682": 0.025,
		"683": 0.05,
		"593": 0.05,
		"594": 0.15,
		"453": 0.05,
		"454": 0.15,
		"565": 0.05,
		"566": 0.15,
		"668": 0.15,
		"669": 0.3
	},
	
	"gift": 
	[		
		{	"cd": 100,	"txt": 1300808,	"m": 50000	},
		{	"cd": 250,	"continue": 1	},
		{	"cd": 500,	"s": 1	},

		{	"cd": 750,	"m": 100000 },
		{	"cd": 1000,	"c": 181,	"count": 3	},
		{	"cd": 1400,	"c": 774,	"count": 3	},	
		{	"cd": 1800,	"stamina": 1	},

	{	"cd": 2200,	"c": 847,	"count": 1	},
	
		{	"cd": 2600,	"c": 319,	"count": 1	},	
		{	"cd": 3000,	"c": 774,	"count": 3	},	
		{	"cd": 3500,	"s": 1	},
		
		{	"cd": 4000,	"c": 774,	"count": 5	},
		{	"cd": 4500,	"c": 319,	"count": 2 },
		{	"cd": 5000,	"gacha": 1 },
		{	"cd": 5500,	"c": 774,	"count": 7	},
		{	"cd": 6000,	"continue": 2	},
		{	"cd": 6500,	"stamina": 1	},
		{	"cd": 7000,	"c": 159,	"count": 1	},
		
	{	"cd": 7500,	"c": 847,	"count": 1	},
	
		{	"cd": 8000,	"s": 1	},
		
		{	"cd": 8500,	"c": 774,	"count": 9	},
		{	"cd": 9000,	"c": 642,	"count": 1	},
		{	"cd": 9500,	"c": 181,	"count": 5	},	
		{	"cd": 10000,	"c": 775,	"count": 3	},
		{	"cd": 11250,	"c": 319,	"count": 3	},
		{	"cd": 12500,	"stamina": 1	},

	{	"cd": 13750,	"c": 847,	"count": 1	},

		{	"cd": 15000,	"c": 450,	"count": 1	},
		{	"cd": 16250,	"c": 642,	"count": 1	},
		{	"cd": 17500,	"s": 1	},
		{	"cd": 18750,	"c": 450,	"count": 2	},

	{	"cd": 20000,	"c": 847,	"count": 1	},

		{	"cd": 21250,	"c": 775,	"count": 5	},
		{	"cd": 22500,	"stamina": 1	},
		{	"cd": 23750,	"c": 450,	"count": 3	},

	{	"cd": 25000,	"c": 847,	"count": 1	},
		
		{	"cd": 26250,	"c": 642,	"count": 1	},
		{	"cd": 27500,	"s": 1	},
		{	"cd": 28750,	"c": 159,	"count": 1	},

	{	"cd": 30000,	"c": 847,	"count": 1	},

		{	"cd": 32500,	"c": 775,	"count": 7	},
		{	"cd": 35000,	"stamina": 1	},

	{	"cd": 37500,	"c": 847,	"count": 1	},

		{	"cd": 40000,	"c": 643,	"count": 1	},
		{	"cd": 42500,	"s": 1	},

	{	"cd": 45000,	"c": 847,	"count": 1	},

		{	"cd": 47500,	"c": 776,	"count": 5	},
		{	"cd": 50000,	"s": 1	},

	{	"cd": 52500,	"c": 847,	"count": 1	},

		{	"cd": 55000,	"c": 643,	"count": 1	},
		{	"cd": 57500,	"s": 1	},

	{	"cd": 60000,	"c": 847,	"count": 1	},
		
		{	"cd": 62500,	"c": 776,	"count": 5	},
		{	"cd": 65000,	"s": 1	},

	{	"cd": 67500,	"c": 847,	"count": 1	},
		
		{	"cd": 70000,	"gacha": 1	},
		{	"cd": 72500,	"s": 1	},

	{	"cd": 75000,	"c": 847,	"count": 1	},

		{	"cd": 80000,	"s": 1	},
		{	"cd": 85000,	"s": 1	},
		{	"cd": 90000,	"s": 1	},
		{	"cd": 95000,	"s": 1	},
		
	{	"cd": 100000,	"c": 776,	"count": 9	},
	
		{	"cd": 105000,	"s": 1	},
		{	"cd": 110000,	"s": 2	},
		{	"cd": 115000,	"s": 2	},
		{	"cd": 120000,	"s": 2	},
		{	"cd": 130000,	"gacha": 1	},
		{	"cd": 140000,	"s": 2	},
		{	"cd": 150000,	"s": 2	},
		{	"cd": 160000,	"s": 2	},
		{	"cd": 170000,	"s": 3	},
		{	"cd": 180000,	"s": 3	},
		{	"cd": 190000,	"s": 3	},
		{	"cd": 200000,	"gacha": 1 }
	],
	"rankgift": 
	[
		{	"begin": 1,	"end": 1,	"c": 610,	"cc": 1,	"txt": 1300813	},
		{	"begin": 2,	"end": 2,	"c": 610,	"cc": 1,	"txt": 1300813	},
		{	"begin": 3,	"end": 3,	"c": 610,	"cc": 1,	"txt": 1300813	},
		
		{	"begin": 1,	"end": 10,	"c": 848,	"cc": 4 },
		{	"begin": 11,	"end": 25,	"c": 848,	"cc": 3 },
		{	"begin": 26,	"end": 100,	"c": 848,	"cc": 2 },
		{	"begin": 101,	"end": 200,	"c": 848,	"cc": 1 },

		{	"begin": 777,	"end": 777,	"c": 610,	"cc": 1,	"txt": 1300813	},

		{	"begin": 201,	"end": 1000,	"gacha": 1 },
		{	"begin": 1001,	"end": 2000,	"s": 3 },
		{	"begin": 2001,	"end": 20000,	"s": 1 }
	]
	
}